Metadata-Version: 2.1
Name: pythonpractgurovns
Version: 0.0.1
Summary: My Package
Author: Gurov Nikita
Author-email: your@domain.com
